authenticator_backup/__init__.py
authenticator_backup/__main__.py
authenticator_backup/_meta.py
authenticator_backup/backup.py
authenticator_backup/gui.py
authenticator_backup/restore.py
authenticator_backup/utils.py
authenticator_backup-0.1.2.dist-info/LICENSE
authenticator_backup-0.1.2.dist-info/METADATA
authenticator_backup-0.1.2.dist-info/WHEEL
authenticator_backup-0.1.2.dist-info/top_level.txt
authenticator_backup-0.1.2.dist-info/RECORD
