Metadata-Version: 2.1
Name: authenticator-backup
Version: 0.1.2
Summary: Tool to backup Google Authenticator to a GPG encrypted file
Home-page: https://github.com/mikeshultz/authenticator_backup
Author: Mike Shultz
Author-email: mike@mikeshultz.com
License: UNKNOWN
Keywords: google authenticator backup
Platform: UNKNOWN
Classifier: Development Status :: 3 - Alpha
Classifier: Intended Audience :: End Users/Desktop
Classifier: Topic :: Security :: Cryptography
Classifier: Topic :: System :: Archiving :: Backup
Classifier: License :: OSI Approved :: GNU General Public License v3 or later (GPLv3+)
Classifier: Programming Language :: Python :: 3
Classifier: Programming Language :: Python :: 3.6
Classifier: Programming Language :: Python :: 3.7
Classifier: Programming Language :: Python :: 3.8
Requires-Dist: opencv-python (~=4.5.5.64)
Requires-Dist: python-gnupg (~=0.4.9)
Requires-Dist: pyzbar (~=0.1.9)
Requires-Dist: qrcode[pil] (~=7.3.1)
Provides-Extra: dev
Requires-Dist: autoflake (~=1.4) ; extra == 'dev'
Requires-Dist: black (>=21.11b1) ; extra == 'dev'
Requires-Dist: bump2version (~=1.0.1) ; extra == 'dev'
Requires-Dist: isort (>=5.10.1) ; extra == 'dev'
Requires-Dist: mypy (>=0.910) ; extra == 'dev'
Requires-Dist: setuptools (>=44.0.0) ; extra == 'dev'
Requires-Dist: twine (>=3.1.1) ; extra == 'dev'
Requires-Dist: wheel (>=0.33.6) ; extra == 'dev'
